{
  "platform": "wechat",
  "title": "﻿从 AI 提效到 AI 变现：普通人更现实的一条路",
  "digest": "很多人一学 AI，就会直接问：怎么赚钱。这个问题没有错，但如果一开始就只盯着赚钱，很容易忽略最关键的一步：你有没有先把 AI 用到自己身上，跑出一个稳定结果。对普通人来说，从 AI 提效走到 AI 变现，通常比一上来就追",
  "source_article": "",
  "cover_path": "images/01_公众号封面_标题版_2.35比1.png",
  "body_image_paths": [
    "images/02_为什么别一开始只盯着AI赚钱.png",
    "images/03_第一阶段先把AI变成提效工具.png",
    "images/04_第二阶段把提效整理成路径.png",
    "images/05_第三阶段再进入变现动作.png",
    "images/06_普通人更现实的一条路是先稳再放大.png"
  ],
  "status": "draft-ready",
  "legacy": {
    "title": "从 AI 提效到 AI 变现：普通人更现实的一条路",
    "date": "20260629",
    "cta_keyword": "资料",
    "cta_resource": "《从提效到变现的 3 段路径图》",
    "image_files": [
      "01_公众号封面.png",
      "02_为什么别一开始只盯着AI赚钱.png",
      "03_第一阶段先把AI变成提效工具.png",
      "04_第二阶段把提效整理成路径.png",
      "05_第三阶段再进入变现动作.png",
      "06_普通人更现实的一条路是先稳再放大.png"
    ],
    "theme": "studio-pop",
    "cover_hook": "先提效再变现",
    "cover_kicker": "这条更现实",
    "cover_variant": "spotlight-right",
    "cover_prompt": "Chinese social-media cover background, clear rising path from laptop productivity to simple monetization milestones, one realistic path instead of luxury fantasy, bright orange pop style, no text, no watermark.",
    "cover_image": "01_公众号封面.png"
  }
}